MANIFEST.in
README
setup.py
pique/__init__.py
pique/analysis.py
pique/constants.py
pique/data.py
pique/fileIO.py
pique/mapmaker.c
pique/mapmaker.pyx
pique/peak.pyx
pique/processing.py
pique/runtime.py
pique.egg-info/PKG-INFO
pique.egg-info/SOURCES.txt
pique.egg-info/dependency_links.txt
pique.egg-info/top_level.txt
pique/tests/__init__.py
scripts/pique