Metadata-Version: 1.1
Name: pique
Version: 0.1.7
Summary: An efficient peak finder for high coverage ChIP-seq experiments.
Home-page: https://github.com/ryneches/pique
Author: Russell Neches
Author-email: ryneches@ucdavis.edu
License: BSD
Platform: UNKNOWN
Classifier: Development Status :: 4 - Beta
Classifier: Topic :: Scientific/Engineering :: Bio-Informatics
Classifier: Programming Language :: Cython
Classifier: Programming Language :: Python :: 2.7
Classifier: License :: OSI Approved :: BSD License
Requires: numpy
Requires: scipy
Requires: cython
Requires: pysam
